{
  "timestamp": "2026-03-19T10:08:12.844126+00:00",
  "layers": {
    "1_12d_x4": {
      "S": {
        "magnitude": 1.5708256420455238,
        "proj_magnitude": 2.052166011626487,
        "resonance": 0.6498935379337818,
        "total": 0.29018258575269207
      },
      "F": {
        "magnitude": 1.73034476055513,
        "proj_magnitude": 1.7852713843376657,
        "resonance": 0.6570215180542177,
        "total": 0.2654769769570189
      },
      "C": {
        "magnitude": 1.72678593993101,
        "proj_magnitude": 1.750088176324802,
        "resonance": 0.635160782413153,
        "total": 0.2599951466363426
      },
      "R": {
        "magnitude": 1.7234146458832753,
        "proj_magnitude": 1.830666674336192,
        "resonance": 0.6440146174111996,
        "total": 0.2651440895395846
      }
    },
    "3_momentum": {
      "balance": 0.1546837449339945,
      "golden_fit": 0.9017667696216494,
      "cycles": 67
    },
    "4_poles": {
      "pole_a_health": 0.9603288163441229,
      "pole_b_health": 0.7315914176918477,
      "orthogonality": 0.6186328474491376,
      "completeness": 1.0,
      "is_4d": true
    },
    "6_resonance_8d": {
      "truth": 0.0,
      "coherence": 0.0,
      "novelty": 0.0,
      "compression": 0.0,
      "safety": 0.0,
      "utility": 0.0,
      "vitality": 0.0,
      "convergence": 0.0
    },
    "8_hologram": {
      "values": [
        4.201202,
        0.399214,
        1.67717951,
        3.801988,
        3.670202,
        0.348342,
        1.27848475,
        3.32186,
        0.5,
        0.0,
        0.0,
        0.5,
        4.558202,
        0.433423,
        1.97562752,
        4.12478
      ],
      "hash": "d267e6c4be19c078"
    }
  },
  "elapsed_seconds": 1.703334093093872
}